cc_warmup_pkg/__init__.py
cc_warmup_pkg/data_structures.py
cc_warmup_pkg/main.py
cc_warmup_pkg/warmup_integration.py
cc_warmup_pkg/aggregators/__init__.py
cc_warmup_pkg/aggregators/cross_project_aggregator.py
cc_warmup_pkg/analyzers/__init__.py
cc_warmup_pkg/analyzers/session_analyzer.py
cc_warmup_pkg/categorizers/__init__.py
cc_warmup_pkg/categorizers/message_categorizer.py
cc_warmup_pkg/extractors/__init__.py
cc_warmup_pkg/extractors/file_scanner.py
cc_warmup_pkg/extractors/global_session_processor.py
cc_warmup_pkg/extractors/improved_warmup_detector.py
cc_warmup_pkg/extractors/jsonl_parser.py
cc_warmup_pkg/extractors/project_extractor.py
cc_warmup_pkg/integration/__init__.py
cc_warmup-1.1.1.dist-info/METADATA
cc_warmup-1.1.1.dist-info/WHEEL
cc_warmup-1.1.1.dist-info/entry_points.txt
cc_warmup-1.1.1.dist-info/top_level.txt
cc_warmup-1.1.1.dist-info/RECORD
