Metadata-Version: 2.4
Name: cc-warmup
Version: 1.1.1
Summary: A CLI tool to maximize Claude Code usage blocks with intelligent session warming and comprehensive project analytics.
Author-email: Your Name <you@example.com>
Project-URL: Homepage, https://github.com/your-username/cc-warmup
Project-URL: Bug Tracker, https://github.com/your-username/cc-warmup/issues
Classifier: Programming Language :: Python :: 3
Classifier: License :: OSI Approved :: MIT License
Classifier: Operating System :: OS Independent
Classifier: Topic :: Terminals
Classifier: Topic :: Utilities
Requires-Python: >=3.8
Requires-Dist: tabulate>=0.9.0
